bosdyn/__init__.py
bosdyn/client/__init__.py
bosdyn/client/__main__.py
bosdyn/client/area_callback.py
bosdyn/client/area_callback_region_handler_base.py
bosdyn/client/area_callback_service_runner.py
bosdyn/client/area_callback_service_servicer.py
bosdyn/client/area_callback_service_utils.py
bosdyn/client/arm_surface_contact.py
bosdyn/client/async_tasks.py
bosdyn/client/audio_visual.py
bosdyn/client/audio_visual_helpers.py
bosdyn/client/auth.py
bosdyn/client/auto_return.py
bosdyn/client/autowalk.py
bosdyn/client/bddf.py
bosdyn/client/bddf_download.py
bosdyn/client/channel.py
bosdyn/client/command_line.py
bosdyn/client/common.py
bosdyn/client/data_acquisition.py
bosdyn/client/data_acquisition_helpers.py
bosdyn/client/data_acquisition_plugin.py
bosdyn/client/data_acquisition_plugin_service.py
bosdyn/client/data_acquisition_store.py
bosdyn/client/data_buffer.py
bosdyn/client/data_chunk.py
bosdyn/client/data_service.py
bosdyn/client/directory.py
bosdyn/client/directory_registration.py
bosdyn/client/docking.py
bosdyn/client/door.py
bosdyn/client/error_callback_result.py
bosdyn/client/estop.py
bosdyn/client/exceptions.py
bosdyn/client/fault.py
bosdyn/client/frame_helpers.py
bosdyn/client/graph_nav.py
bosdyn/client/gripper_camera_param.py
bosdyn/client/image.py
bosdyn/client/image_service_helpers.py
bosdyn/client/inverse_kinematics.py
bosdyn/client/ir_enable_disable.py
bosdyn/client/keepalive.py
bosdyn/client/lease.py
bosdyn/client/lease_resource_hierarchy.py
bosdyn/client/lease_validator.py
bosdyn/client/license.py
bosdyn/client/local_grid.py
bosdyn/client/log_status.py
bosdyn/client/manipulation_api_client.py
bosdyn/client/map_processing.py
bosdyn/client/math_helpers.py
bosdyn/client/metrics_logging.py
bosdyn/client/network_compute_bridge_client.py
bosdyn/client/payload.py
bosdyn/client/payload_registration.py
bosdyn/client/payload_software_update.py
bosdyn/client/payload_software_update_initiation.py
bosdyn/client/point_cloud.py
bosdyn/client/power.py
bosdyn_client-5.0.1.dist-info/METADATA
bosdyn_client-5.0.1.dist-info/WHEEL
bosdyn_client-5.0.1.dist-info/top_level.txt
bosdyn_client-5.0.1.dist-info/RECORD
